{
  "name": "space-bard-2",
  "title": "Space Bard 2e",
  "description": "",
  "version": "0.2.6",
  "author": "",
  "authors": [
    {
      "name": "",
      "email": "",
      "url": ""
    }
  ],
  "scripts": [],
  "esmodules": ["space-bard-2.js"],
  "styles": ["space-bard-2.css"],
  "packs": [],
  "languages": [],
  "gridDistance": 1,
  "gridUnits": "",
  "minimumCoreVersion": "0.5.0",
  "compatibleCoreVersion": "0.5.0",
  "url": "https://github.com/khawkin2/space-bard-2.git",
  "manifest": "",
  "download": "",
  "license": "",
  "readme": "",
  "bugs": "",
  "changelog": ""
}